fuse_toolkit/__init__.py
fuse_toolkit/cell_similarity_metrics.py
fuse_toolkit/experiment.py
fuse_toolkit/frame_by_frame.py
fuse_toolkit/img_processing.py
fuse_toolkit/lineage_management.py
fuse_toolkit/signal_derivation.py
tests/__init__.py
tests/experiment_test.py
fuse_toolkit-0.1.0b20.dist-info/LICENSE
fuse_toolkit-0.1.0b20.dist-info/METADATA
fuse_toolkit-0.1.0b20.dist-info/WHEEL
fuse_toolkit-0.1.0b20.dist-info/top_level.txt
fuse_toolkit-0.1.0b20.dist-info/RECORD
