Metadata-Version: 2.1
Name: fuse_toolkit
Version: 0.1.0b20
Summary: FUSE toolkit supports fluorescent cell image alignment and analysis.
Author: Shani Zuniga
Author-email: shani.zuniga@gmail.com
License: MIT
Project-URL: Source Code, https://github.com/shanizu/FUSE
Classifier: Development Status :: 4 - Beta
Classifier: Intended Audience :: Science/Research
Classifier: License :: OSI Approved :: MIT License
Classifier: Programming Language :: Python :: 3
Classifier: Topic :: Scientific/Engineering
License-File: LICENSE
Requires-Dist: numpy
Requires-Dist: pandas
Requires-Dist: Pillow
Requires-Dist: tqdm
Requires-Dist: scipy
Requires-Dist: cellpose
Requires-Dist: matplotlib
Requires-Dist: scikit-image
Requires-Dist: scikit-learn
Requires-Dist: tensorflow
